qrspy/__init__.py
qrspy/qrspy.py
qrspy-1.0.0.dist-info/LICENSE
qrspy-1.0.0.dist-info/METADATA
qrspy-1.0.0.dist-info/WHEEL
qrspy-1.0.0.dist-info/top_level.txt
qrspy-1.0.0.dist-info/RECORD
