Metadata-Version: 2.1
Name: qrspy
Version: 1.0.0
Summary: Project forked from clintcarr.
Home-page: https://github.com/rumen-vasilev/qrspy
Author: Rumen Vasilev
Author-email: rumen.vasilev@gmail.com
License: Apache 2.0
Classifier: Programming Language :: Python :: 3
Classifier: License :: OSI Approved :: MIT License
Classifier: Operating System :: OS Independent
Requires-Python: >=3.6
License-File: LICENSE
Requires-Dist: requests >=2.32.3
Requires-Dist: requests-ntlm >=1.2.0
